{
	"type": "GenericCrafter",
	"name": "Hexite Furnace",
	"description": "Makes the purest form of Hexite ever conceived.",
	"size": 3,
	"outputItem": {
		"item": "engineer",
		"amount": 1
	},
	"drawer": {
		"type": "drawMulti",
		"drawers": [
			{
			"type": "drawDefault"
			},
			{
			"type": "drawFlame"
			}
		]
	},
	"hasPower": true,
	"hasItems": true,
	"itemCapacity": 24,
	"craftTime": 120,
	"updateEffect": "smeltsmoke",
	"drawLiquidLight": true,
	"consumes": {
		"power": 5,
		"items": {
			"items": [{
					"item": "sand",
					"amount": 12
				},
				{
					"item": "titanium",
					"amount": 8
				},
				{
					"item": "graphite",
					"amount": 6
				}
			]
		}
	},
	"requirements": [
		{
			"item": "titanium",
			"amount": 140
		},
		{
			"item": "thorium",
			"amount": 110
		},
		{
			"item": "graphite",
			"amount": 125
		},
		{
			"item": "lead",
			"amount": 225
		}
	],
	"category": "crafting",
	"research": "silicon-smelter"
}